dash_user_tracker/__init__.py
dash_user_tracker/analytics.py
dash_user_tracker/http_repository.py
dash_user_tracker/ignore_routes.py
dash_user_tracker/repository.py
dash_user_tracker/routers.py
dash_user_tracker/tracker.py
dash_user_tracker/version.py
dash_user_tracker-1.2.0.dist-info/LICENSE
dash_user_tracker-1.2.0.dist-info/METADATA
dash_user_tracker-1.2.0.dist-info/WHEEL
dash_user_tracker-1.2.0.dist-info/RECORD
