Metadata-Version: 2.3
Name: dash-user-tracker
Version: 1.2.0
Summary: Library to track user interactions in Dash applications
Author: Cesar Flores
Author-email: cesar@qdt.ai
Requires-Python: >=3.9
Classifier: Programming Language :: Python :: 3
Classifier: Programming Language :: Python :: 3.9
Classifier: Programming Language :: Python :: 3.10
Classifier: Programming Language :: Python :: 3.11
Classifier: Programming Language :: Python :: 3.12
Classifier: Programming Language :: Python :: 3.13
Requires-Dist: aiohttp (>=3.11.11,<4.0.0)
Requires-Dist: dash (>=2.0.0,<3.0.0)
Requires-Dist: requests (>=2.32.3,<3.0.0)
